{
  "timestamp": "2026-03-29T23:06:31.614Z",
  "commitSha": "a673e11e855bcd58a852be1e3cf553098ff4da1d",
  "runType": "newHint",
  "exportMode": "full",
  "levelCount": 0,
  "statusCounts": {
    "success": 0,
    "timeout": 0,
    "noSolutionInconclusive": 0,
    "noSolutionProven": 0,
    "aborted": 0,
    "error": 0
  },
  "failingLevels": {
    "total": 0,
    "byStatus": {
      "timeout": 0,
      "noSolutionInconclusive": 0,
      "noSolutionProven": 0,
      "aborted": 0,
      "error": 0
    },
    "levelNumbers": [],
    "details": []
  },
  "qualitySignals": {
    "producedHintValidCount": 0,
    "contradictionRecoveryActivatedCount": 0,
    "preExpansionAbortUnexpectedExceptionCount": 0
  },
  "performance": {
    "hintTimeMsAvg": null,
    "totalSolveTimeMsAvg": null,
    "maxSolveTimeMs": null
  },
  "levels": [],
  "levelTransitionSummary": {
    "comparedAgainst": {
      "timestamp": null,
      "runType": "newHint",
      "exportMode": "full",
      "levelCount": 133
    },
    "counters": {
      "improved": 0,
      "regressed": 0,
      "statusChanged": 0,
      "telemetryChanged": 0,
      "newlyAddedLevels": 0,
      "removedLevels": 133
    },
    "failureFamilyMigration": {},
    "changedLevels": [
      {
        "levelNumber": 1,
        "transition": "removed-level",
        "previous": {
          "status": "success",
          "hasError": false,
          "failureFamily": "success"
        }
      },
      {
        "levelNumber": 2,
        "transition": "removed-level",
        "previous": {
          "status": "success",
          "hasError": false,
          "failureFamily": "success"
        }
      },
      {
        "levelNumber": 3,
        "transition": "removed-level",
        "previous": {
          "status": "success",
          "hasError": false,
          "failureFamily": "success"
        }
      },
      {
        "levelNumber": 4,
        "transition": "removed-level",
        "previous": {
          "status": "success",
          "hasError": false,
          "failureFamily": "success"
        }
      },
      {
        "levelNumber": 5,
        "transition": "removed-level",
        "previous": {
          "status": "success",
          "hasError": false,
          "failureFamily": "success"
        }
      },
      {
        "levelNumber": 6,
        "transition": "removed-level",
        "previous": {
          "status": "success",
          "hasError": false,
          "failureFamily": "success"
        }
      },
      {
        "levelNumber": 7,
        "transition": "removed-level",
        "previous": {
          "status": "success",
          "hasError": false,
          "failureFamily": "success"
        }
      },
      {
        "levelNumber": 8,
        "transition": "removed-level",
        "previous": {
          "status": "success",
          "hasError": false,
          "failureFamily": "success"
        }
      },
      {
        "levelNumber": 9,
        "transition": "removed-level",
        "previous": {
          "status": "success",
          "hasError": false,
          "failureFamily": "success"
        }
      },
      {
        "levelNumber": 10,
        "transition": "removed-level",
        "previous": {
          "status": "success",
          "hasError": false,
          "failureFamily": "success"
        }
      },
      {
        "levelNumber": 11,
        "transition": "removed-level",
        "previous": {
          "status": "success",
          "hasError": false,
          "failureFamily": "success"
        }
      },
      {
        "levelNumber": 12,
        "transition": "removed-level",
        "previous": {
          "status": "success",
          "hasError": false,
          "failureFamily": "success"
        }
      },
      {
        "levelNumber": 13,
        "transition": "removed-level",
        "previous": {
          "status": "success",
          "hasError": false,
          "failureFamily": "success"
        }
      },
      {
        "levelNumber": 14,
        "transition": "removed-level",
        "previous": {
          "status": "success",
          "hasError": false,
          "failureFamily": "success"
        }
      },
      {
        "levelNumber": 15,
        "transition": "removed-level",
        "previous": {
          "status": "success",
          "hasError": false,
          "failureFamily": "success"
        }
      },
      {
        "levelNumber": 16,
        "transition": "removed-level",
        "previous": {
          "status": "success",
          "hasError": false,
          "failureFamily": "success"
        }
      },
      {
        "levelNumber": 17,
        "transition": "removed-level",
        "previous": {
          "status": "success",
          "hasError": false,
          "failureFamily": "success"
        }
      },
      {
        "levelNumber": 18,
        "transition": "removed-level",
        "previous": {
          "status": "success",
          "hasError": false,
          "failureFamily": "success"
        }
      },
      {
        "levelNumber": 19,
        "transition": "removed-level",
        "previous": {
          "status": "success",
          "hasError": false,
          "failureFamily": "success"
        }
      },
      {
        "levelNumber": 20,
        "transition": "removed-level",
        "previous": {
          "status": "success",
          "hasError": false,
          "failureFamily": "success"
        }
      },
      {
        "levelNumber": 21,
        "transition": "removed-level",
        "previous": {
          "status": "success",
          "hasError": false,
          "failureFamily": "success"
        }
      },
      {
        "levelNumber": 22,
        "transition": "removed-level",
        "previous": {
          "status": "success",
          "hasError": false,
          "failureFamily": "success"
        }
      },
      {
        "levelNumber": 23,
        "transition": "removed-level",
        "previous": {
          "status": "success",
          "hasError": false,
          "failureFamily": "success"
        }
      },
      {
        "levelNumber": 24,
        "transition": "removed-level",
        "previous": {
          "status": "success",
          "hasError": false,
          "failureFamily": "success"
        }
      },
      {
        "levelNumber": 25,
        "transition": "removed-level",
        "previous": {
          "status": "success",
          "hasError": false,
          "failureFamily": "success"
        }
      },
      {
        "levelNumber": 26,
        "transition": "removed-level",
        "previous": {
          "status": "timeout",
          "hasError": true,
          "failureFamily": "error"
        }
      },
      {
        "levelNumber": 27,
        "transition": "removed-level",
        "previous": {
          "status": "success",
          "hasError": false,
          "failureFamily": "success"
        }
      },
      {
        "levelNumber": 28,
        "transition": "removed-level",
        "previous": {
          "status": "success",
          "hasError": false,
          "failureFamily": "success"
        }
      },
      {
        "levelNumber": 29,
        "transition": "removed-level",
        "previous": {
          "status": "success",
          "hasError": false,
          "failureFamily": "success"
        }
      },
      {
        "levelNumber": 30,
        "transition": "removed-level",
        "previous": {
          "status": "success",
          "hasError": false,
          "failureFamily": "success"
        }
      },
      {
        "levelNumber": 31,
        "transition": "removed-level",
        "previous": {
          "status": "success",
          "hasError": false,
          "failureFamily": "success"
        }
      },
      {
        "levelNumber": 32,
        "transition": "removed-level",
        "previous": {
          "status": "success",
          "hasError": false,
          "failureFamily": "success"
        }
      },
      {
        "levelNumber": 33,
        "transition": "removed-level",
        "previous": {
          "status": "success",
          "hasError": false,
          "failureFamily": "success"
        }
      },
      {
        "levelNumber": 34,
        "transition": "removed-level",
        "previous": {
          "status": "success",
          "hasError": false,
          "failureFamily": "success"
        }
      },
      {
        "levelNumber": 35,
        "transition": "removed-level",
        "previous": {
          "status": "success",
          "hasError": false,
          "failureFamily": "success"
        }
      },
      {
        "levelNumber": 36,
        "transition": "removed-level",
        "previous": {
          "status": "success",
          "hasError": false,
          "failureFamily": "success"
        }
      },
      {
        "levelNumber": 37,
        "transition": "removed-level",
        "previous": {
          "status": "success",
          "hasError": false,
          "failureFamily": "success"
        }
      },
      {
        "levelNumber": 38,
        "transition": "removed-level",
        "previous": {
          "status": "success",
          "hasError": false,
          "failureFamily": "success"
        }
      },
      {
        "levelNumber": 39,
        "transition": "removed-level",
        "previous": {
          "status": "success",
          "hasError": false,
          "failureFamily": "success"
        }
      },
      {
        "levelNumber": 40,
        "transition": "removed-level",
        "previous": {
          "status": "success",
          "hasError": false,
          "failureFamily": "success"
        }
      },
      {
        "levelNumber": 41,
        "transition": "removed-level",
        "previous": {
          "status": "success",
          "hasError": false,
          "failureFamily": "success"
        }
      },
      {
        "levelNumber": 42,
        "transition": "removed-level",
        "previous": {
          "status": "success",
          "hasError": false,
          "failureFamily": "success"
        }
      },
      {
        "levelNumber": 43,
        "transition": "removed-level",
        "previous": {
          "status": "success",
          "hasError": false,
          "failureFamily": "success"
        }
      },
      {
        "levelNumber": 44,
        "transition": "removed-level",
        "previous": {
          "status": "success",
          "hasError": false,
          "failureFamily": "success"
        }
      },
      {
        "levelNumber": 45,
        "transition": "removed-level",
        "previous": {
          "status": "success",
          "hasError": false,
          "failureFamily": "success"
        }
      },
      {
        "levelNumber": 46,
        "transition": "removed-level",
        "previous": {
          "status": "success",
          "hasError": false,
          "failureFamily": "success"
        }
      },
      {
        "levelNumber": 47,
        "transition": "removed-level",
        "previous": {
          "status": "success",
          "hasError": false,
          "failureFamily": "success"
        }
      },
      {
        "levelNumber": 48,
        "transition": "removed-level",
        "previous": {
          "status": "success",
          "hasError": false,
          "failureFamily": "success"
        }
      },
      {
        "levelNumber": 49,
        "transition": "removed-level",
        "previous": {
          "status": "success",
          "hasError": false,
          "failureFamily": "success"
        }
      },
      {
        "levelNumber": 50,
        "transition": "removed-level",
        "previous": {
          "status": "success",
          "hasError": false,
          "failureFamily": "success"
        }
      },
      {
        "levelNumber": 51,
        "transition": "removed-level",
        "previous": {
          "status": "success",
          "hasError": false,
          "failureFamily": "success"
        }
      },
      {
        "levelNumber": 52,
        "transition": "removed-level",
        "previous": {
          "status": "success",
          "hasError": false,
          "failureFamily": "success"
        }
      },
      {
        "levelNumber": 53,
        "transition": "removed-level",
        "previous": {
          "status": "success",
          "hasError": false,
          "failureFamily": "success"
        }
      },
      {
        "levelNumber": 54,
        "transition": "removed-level",
        "previous": {
          "status": "success",
          "hasError": false,
          "failureFamily": "success"
        }
      },
      {
        "levelNumber": 55,
        "transition": "removed-level",
        "previous": {
          "status": "success",
          "hasError": false,
          "failureFamily": "success"
        }
      },
      {
        "levelNumber": 56,
        "transition": "removed-level",
        "previous": {
          "status": "success",
          "hasError": false,
          "failureFamily": "success"
        }
      },
      {
        "levelNumber": 57,
        "transition": "removed-level",
        "previous": {
          "status": "success",
          "hasError": false,
          "failureFamily": "success"
        }
      },
      {
        "levelNumber": 58,
        "transition": "removed-level",
        "previous": {
          "status": "success",
          "hasError": false,
          "failureFamily": "success"
        }
      },
      {
        "levelNumber": 59,
        "transition": "removed-level",
        "previous": {
          "status": "success",
          "hasError": false,
          "failureFamily": "success"
        }
      },
      {
        "levelNumber": 60,
        "transition": "removed-level",
        "previous": {
          "status": "success",
          "hasError": false,
          "failureFamily": "success"
        }
      },
      {
        "levelNumber": 61,
        "transition": "removed-level",
        "previous": {
          "status": "success",
          "hasError": false,
          "failureFamily": "success"
        }
      },
      {
        "levelNumber": 62,
        "transition": "removed-level",
        "previous": {
          "status": "success",
          "hasError": false,
          "failureFamily": "success"
        }
      },
      {
        "levelNumber": 63,
        "transition": "removed-level",
        "previous": {
          "status": "success",
          "hasError": false,
          "failureFamily": "success"
        }
      },
      {
        "levelNumber": 64,
        "transition": "removed-level",
        "previous": {
          "status": "success",
          "hasError": false,
          "failureFamily": "success"
        }
      },
      {
        "levelNumber": 65,
        "transition": "removed-level",
        "previous": {
          "status": "success",
          "hasError": false,
          "failureFamily": "success"
        }
      },
      {
        "levelNumber": 66,
        "transition": "removed-level",
        "previous": {
          "status": "success",
          "hasError": false,
          "failureFamily": "success"
        }
      },
      {
        "levelNumber": 67,
        "transition": "removed-level",
        "previous": {
          "status": "success",
          "hasError": false,
          "failureFamily": "success"
        }
      },
      {
        "levelNumber": 68,
        "transition": "removed-level",
        "previous": {
          "status": "success",
          "hasError": false,
          "failureFamily": "success"
        }
      },
      {
        "levelNumber": 69,
        "transition": "removed-level",
        "previous": {
          "status": "success",
          "hasError": false,
          "failureFamily": "success"
        }
      },
      {
        "levelNumber": 70,
        "transition": "removed-level",
        "previous": {
          "status": "success",
          "hasError": false,
          "failureFamily": "success"
        }
      },
      {
        "levelNumber": 71,
        "transition": "removed-level",
        "previous": {
          "status": "success",
          "hasError": false,
          "failureFamily": "success"
        }
      },
      {
        "levelNumber": 72,
        "transition": "removed-level",
        "previous": {
          "status": "success",
          "hasError": false,
          "failureFamily": "success"
        }
      },
      {
        "levelNumber": 73,
        "transition": "removed-level",
        "previous": {
          "status": "success",
          "hasError": false,
          "failureFamily": "success"
        }
      },
      {
        "levelNumber": 74,
        "transition": "removed-level",
        "previous": {
          "status": "success",
          "hasError": false,
          "failureFamily": "success"
        }
      },
      {
        "levelNumber": 75,
        "transition": "removed-level",
        "previous": {
          "status": "success",
          "hasError": false,
          "failureFamily": "success"
        }
      },
      {
        "levelNumber": 76,
        "transition": "removed-level",
        "previous": {
          "status": "success",
          "hasError": false,
          "failureFamily": "success"
        }
      },
      {
        "levelNumber": 77,
        "transition": "removed-level",
        "previous": {
          "status": "success",
          "hasError": false,
          "failureFamily": "success"
        }
      },
      {
        "levelNumber": 78,
        "transition": "removed-level",
        "previous": {
          "status": "success",
          "hasError": false,
          "failureFamily": "success"
        }
      },
      {
        "levelNumber": 79,
        "transition": "removed-level",
        "previous": {
          "status": "success",
          "hasError": false,
          "failureFamily": "success"
        }
      },
      {
        "levelNumber": 80,
        "transition": "removed-level",
        "previous": {
          "status": "success",
          "hasError": false,
          "failureFamily": "success"
        }
      },
      {
        "levelNumber": 81,
        "transition": "removed-level",
        "previous": {
          "status": "success",
          "hasError": false,
          "failureFamily": "success"
        }
      },
      {
        "levelNumber": 82,
        "transition": "removed-level",
        "previous": {
          "status": "success",
          "hasError": false,
          "failureFamily": "success"
        }
      },
      {
        "levelNumber": 83,
        "transition": "removed-level",
        "previous": {
          "status": "success",
          "hasError": false,
          "failureFamily": "success"
        }
      },
      {
        "levelNumber": 84,
        "transition": "removed-level",
        "previous": {
          "status": "success",
          "hasError": false,
          "failureFamily": "success"
        }
      },
      {
        "levelNumber": 85,
        "transition": "removed-level",
        "previous": {
          "status": "success",
          "hasError": false,
          "failureFamily": "success"
        }
      },
      {
        "levelNumber": 86,
        "transition": "removed-level",
        "previous": {
          "status": "success",
          "hasError": false,
          "failureFamily": "success"
        }
      },
      {
        "levelNumber": 87,
        "transition": "removed-level",
        "previous": {
          "status": "success",
          "hasError": false,
          "failureFamily": "success"
        }
      },
      {
        "levelNumber": 88,
        "transition": "removed-level",
        "previous": {
          "status": "success",
          "hasError": false,
          "failureFamily": "success"
        }
      },
      {
        "levelNumber": 89,
        "transition": "removed-level",
        "previous": {
          "status": "success",
          "hasError": false,
          "failureFamily": "success"
        }
      },
      {
        "levelNumber": 90,
        "transition": "removed-level",
        "previous": {
          "status": "success",
          "hasError": false,
          "failureFamily": "success"
        }
      },
      {
        "levelNumber": 91,
        "transition": "removed-level",
        "previous": {
          "status": "success",
          "hasError": false,
          "failureFamily": "success"
        }
      },
      {
        "levelNumber": 92,
        "transition": "removed-level",
        "previous": {
          "status": "timeout",
          "hasError": true,
          "failureFamily": "error"
        }
      },
      {
        "levelNumber": 93,
        "transition": "removed-level",
        "previous": {
          "status": "success",
          "hasError": false,
          "failureFamily": "success"
        }
      },
      {
        "levelNumber": 94,
        "transition": "removed-level",
        "previous": {
          "status": "success",
          "hasError": false,
          "failureFamily": "success"
        }
      },
      {
        "levelNumber": 95,
        "transition": "removed-level",
        "previous": {
          "status": "success",
          "hasError": false,
          "failureFamily": "success"
        }
      },
      {
        "levelNumber": 96,
        "transition": "removed-level",
        "previous": {
          "status": "success",
          "hasError": false,
          "failureFamily": "success"
        }
      },
      {
        "levelNumber": 97,
        "transition": "removed-level",
        "previous": {
          "status": "success",
          "hasError": false,
          "failureFamily": "success"
        }
      },
      {
        "levelNumber": 98,
        "transition": "removed-level",
        "previous": {
          "status": "success",
          "hasError": false,
          "failureFamily": "success"
        }
      },
      {
        "levelNumber": 99,
        "transition": "removed-level",
        "previous": {
          "status": "success",
          "hasError": false,
          "failureFamily": "success"
        }
      },
      {
        "levelNumber": 100,
        "transition": "removed-level",
        "previous": {
          "status": "success",
          "hasError": false,
          "failureFamily": "success"
        }
      },
      {
        "levelNumber": 101,
        "transition": "removed-level",
        "previous": {
          "status": "success",
          "hasError": false,
          "failureFamily": "success"
        }
      },
      {
        "levelNumber": 102,
        "transition": "removed-level",
        "previous": {
          "status": "success",
          "hasError": false,
          "failureFamily": "success"
        }
      },
      {
        "levelNumber": 103,
        "transition": "removed-level",
        "previous": {
          "status": "success",
          "hasError": false,
          "failureFamily": "success"
        }
      },
      {
        "levelNumber": 104,
        "transition": "removed-level",
        "previous": {
          "status": "success",
          "hasError": false,
          "failureFamily": "success"
        }
      },
      {
        "levelNumber": 105,
        "transition": "removed-level",
        "previous": {
          "status": "success",
          "hasError": false,
          "failureFamily": "success"
        }
      },
      {
        "levelNumber": 106,
        "transition": "removed-level",
        "previous": {
          "status": "success",
          "hasError": false,
          "failureFamily": "success"
        }
      },
      {
        "levelNumber": 107,
        "transition": "removed-level",
        "previous": {
          "status": "success",
          "hasError": false,
          "failureFamily": "success"
        }
      },
      {
        "levelNumber": 108,
        "transition": "removed-level",
        "previous": {
          "status": "timeout",
          "hasError": true,
          "failureFamily": "error"
        }
      },
      {
        "levelNumber": 109,
        "transition": "removed-level",
        "previous": {
          "status": "success",
          "hasError": false,
          "failureFamily": "success"
        }
      },
      {
        "levelNumber": 110,
        "transition": "removed-level",
        "previous": {
          "status": "success",
          "hasError": false,
          "failureFamily": "success"
        }
      },
      {
        "levelNumber": 111,
        "transition": "removed-level",
        "previous": {
          "status": "success",
          "hasError": false,
          "failureFamily": "success"
        }
      },
      {
        "levelNumber": 112,
        "transition": "removed-level",
        "previous": {
          "status": "success",
          "hasError": false,
          "failureFamily": "success"
        }
      },
      {
        "levelNumber": 113,
        "transition": "removed-level",
        "previous": {
          "status": "success",
          "hasError": false,
          "failureFamily": "success"
        }
      },
      {
        "levelNumber": 114,
        "transition": "removed-level",
        "previous": {
          "status": "success",
          "hasError": false,
          "failureFamily": "success"
        }
      },
      {
        "levelNumber": 115,
        "transition": "removed-level",
        "previous": {
          "status": "success",
          "hasError": false,
          "failureFamily": "success"
        }
      },
      {
        "levelNumber": 116,
        "transition": "removed-level",
        "previous": {
          "status": "success",
          "hasError": false,
          "failureFamily": "success"
        }
      },
      {
        "levelNumber": 117,
        "transition": "removed-level",
        "previous": {
          "status": "success",
          "hasError": false,
          "failureFamily": "success"
        }
      },
      {
        "levelNumber": 118,
        "transition": "removed-level",
        "previous": {
          "status": "success",
          "hasError": false,
          "failureFamily": "success"
        }
      },
      {
        "levelNumber": 119,
        "transition": "removed-level",
        "previous": {
          "status": "success",
          "hasError": false,
          "failureFamily": "success"
        }
      },
      {
        "levelNumber": 120,
        "transition": "removed-level",
        "previous": {
          "status": "success",
          "hasError": false,
          "failureFamily": "success"
        }
      },
      {
        "levelNumber": 121,
        "transition": "removed-level",
        "previous": {
          "status": "success",
          "hasError": false,
          "failureFamily": "success"
        }
      },
      {
        "levelNumber": 122,
        "transition": "removed-level",
        "previous": {
          "status": "success",
          "hasError": false,
          "failureFamily": "success"
        }
      },
      {
        "levelNumber": 123,
        "transition": "removed-level",
        "previous": {
          "status": "success",
          "hasError": false,
          "failureFamily": "success"
        }
      },
      {
        "levelNumber": 124,
        "transition": "removed-level",
        "previous": {
          "status": "success",
          "hasError": false,
          "failureFamily": "success"
        }
      },
      {
        "levelNumber": 125,
        "transition": "removed-level",
        "previous": {
          "status": "success",
          "hasError": false,
          "failureFamily": "success"
        }
      },
      {
        "levelNumber": 126,
        "transition": "removed-level",
        "previous": {
          "status": "success",
          "hasError": false,
          "failureFamily": "success"
        }
      },
      {
        "levelNumber": 127,
        "transition": "removed-level",
        "previous": {
          "status": "success",
          "hasError": false,
          "failureFamily": "success"
        }
      },
      {
        "levelNumber": 128,
        "transition": "removed-level",
        "previous": {
          "status": "success",
          "hasError": false,
          "failureFamily": "success"
        }
      },
      {
        "levelNumber": 129,
        "transition": "removed-level",
        "previous": {
          "status": "success",
          "hasError": false,
          "failureFamily": "success"
        }
      },
      {
        "levelNumber": 130,
        "transition": "removed-level",
        "previous": {
          "status": "success",
          "hasError": false,
          "failureFamily": "success"
        }
      },
      {
        "levelNumber": 131,
        "transition": "removed-level",
        "previous": {
          "status": "success",
          "hasError": false,
          "failureFamily": "success"
        }
      },
      {
        "levelNumber": 132,
        "transition": "removed-level",
        "previous": {
          "status": "success",
          "hasError": false,
          "failureFamily": "success"
        }
      },
      {
        "levelNumber": 133,
        "transition": "removed-level",
        "previous": {
          "status": "success",
          "hasError": false,
          "failureFamily": "success"
        }
      }
    ],
    "unchangedLevelCount": 0
  }
}
